COPYING
MANIFEST.in
README.rst
buildout.cfg
develop.cfg
requirements.txt
setup.py
version.txt
bob/__init__.py
bob.db.wine.egg-info/PKG-INFO
bob.db.wine.egg-info/SOURCES.txt
bob.db.wine.egg-info/dependency_links.txt
bob.db.wine.egg-info/entry_points.txt
bob.db.wine.egg-info/not-zip-safe
bob.db.wine.egg-info/requires.txt
bob.db.wine.egg-info/top_level.txt
bob/db/__init__.py
bob/db/wine/__init__.py
bob/db/wine/driver.py
bob/db/wine/test.py
bob/db/wine/wine.data
bob/db/wine/wine.names
doc/conf.py
doc/guide.rst
doc/index.rst
doc/py_api.rst